pcmux.sv
module pcmux (
    input  logic [31:0]  ImmExt,
    input  logic [31:0]  PC,
    input  logic         PCSrc,
    output logic [31:0]  PCNext
);

always_comb begin
    if (PCSrc)
        PCNext = ImmExt + PC;
    else
        PCNext = PC + 32'b00000000000000000000000000000100;
end

endmodule

pcreg.sv
module pcreg (
    input  logic         clk,
    input  logic         rst,
    input  logic         PCSrc,
    input  logic [31:0]  ImmExt,
    output logic [31:0]  PC
);

logic [31:0] PCNext;

always_ff @ (posedge clk or posedge rst) begin 
  if (rst) begin
        PC <= 32'b00000000000000000000000000000000;
  end
  else begin
      PC <= PCNext;
  end
    
end

pcmux myPcmux (
  .PC (PC),
  .ImmExt (ImmExt),
  .PCSrc (PCSrc), // 1 means use immediate
  .PCNext (PCNext)
);

endmodule

pcreg.vcd
$version Generated by VerilatedVcd $end
$timescale 1ps $end

 $scope module TOP $end
  $var wire 32 & ImmExt [31:0] $end
  $var wire 32 ' PC [31:0] $end
  $var wire  1 % PCSrc $end
  $var wire  1 # clk $end
  $var wire  1 $ rst $end
  $scope module pcreg $end
   $var wire 32 & ImmExt [31:0] $end
   $var wire 32 ' PC [31:0] $end
   $var wire 32 ( PCNext [31:0] $end
   $var wire  1 % PCSrc $end
   $var wire  1 # clk $end
   $var wire  1 $ rst $end
   $scope module myPcmux $end
    $var wire 32 & ImmExt [31:0] $end
    $var wire 32 ' PC [31:0] $end
    $var wire 32 ( PCNext [31:0] $end
    $var wire  1 % PCSrc $end
   $upscope $end
  $upscope $end
 $upscope $end
$enddefinitions $end


#0
1#
1$
1%
b00000000000000000000000000001000 &
b00000000000000000000000000000000 '
b00000000000000000000000000001000 (
#1
0#
#2
1#
0$
0%
b00000000000000000000000000000100 (
#3
0#
#4
1#
1%
b00000000000000000000000000000100 '
b00000000000000000000000000001100 (
#5
0#
#6
1#
0%
b00000000000000000000000000001100 '
b00000000000000000000000000010000 (
#7
0#
#8
1#
1%
b00000000000000000000000000010000 '
b00000000000000000000000000011000 (
#9
0#
#10
1#
0%
b00000000000000000000000000011000 '
b00000000000000000000000000011100 (
#11
0#
#12
1#
1%
b00000000000000000000000000011100 '
b00000000000000000000000000100100 (
#13
0#
#14
1#
0%
b00000000000000000000000000100100 '
b00000000000000000000000000101000 (
#15
0#
#16
1#
1%
b00000000000000000000000000101000 '
b00000000000000000000000000110000 (
#17
0#
#18
1#
0%
b00000000000000000000000000110000 '
b00000000000000000000000000110100 (
#19
0#
#20
1#
1%
b00000000000000000000000000110100 '
b00000000000000000000000000111100 (
#21
0#
#22
1#
0%
b00000000000000000000000000111100 '
b00000000000000000000000001000000 (
#23
0#
#24
1#
1%
b00000000000000000000000001000000 '
b00000000000000000000000001001000 (
#25
0#
#26
1#
0%
b00000000000000000000000001001000 '
b00000000000000000000000001001100 (
#27
0#
#28
1#
1%
b00000000000000000000000001001100 '
b00000000000000000000000001010100 (
#29
0#
#30
1#
0%
b00000000000000000000000001010100 '
b00000000000000000000000001011000 (
#31
0#
#32
1#
1%
b00000000000000000000000001011000 '
b00000000000000000000000001100000 (
#33
0#
#34
1#
0%
b00000000000000000000000001100000 '
b00000000000000000000000001100100 (
#35
0#
#36
1#
1%
b00000000000000000000000001100100 '
b00000000000000000000000001101100 (
#37
0#
#38
1#
0%
b00000000000000000000000001101100 '
b00000000000000000000000001110000 (
#39
0#
#40
1#
1%
b00000000000000000000000001110000 '
b00000000000000000000000001111000 (
#41
0#
#42
1#
0%
b00000000000000000000000001111000 '
b00000000000000000000000001111100 (
#43
0#
#44
1#
1%
b00000000000000000000000001111100 '
b00000000000000000000000010000100 (
#45
0#
#46
1#
0%
b00000000000000000000000010000100 '
b00000000000000000000000010001000 (
#47
0#
#48
1#
1%
b00000000000000000000000010001000 '
b00000000000000000000000010010000 (
#49
0#
#50
1#
0%
b00000000000000000000000010010000 '
b00000000000000000000000010010100 (
#51
0#
#52
1#
1%
b00000000000000000000000010010100 '
b00000000000000000000000010011100 (
#53
0#
#54
1#
0%
b00000000000000000000000010011100 '
b00000000000000000000000010100000 (
#55
0#
#56
1#
1%
b00000000000000000000000010100000 '
b00000000000000000000000010101000 (
#57
0#
#58
1#
0%
b00000000000000000000000010101000 '
b00000000000000000000000010101100 (
#59
0#
#60
1#
1%
b00000000000000000000000010101100 '
b00000000000000000000000010110100 (
#61
0#
#62
1#
0%
b00000000000000000000000010110100 '
b00000000000000000000000010111000 (
#63
0#
#64
1#
1%
b00000000000000000000000010111000 '
b00000000000000000000000011000000 (
#65
0#
#66
1#
0%
b00000000000000000000000011000000 '
b00000000000000000000000011000100 (
#67
0#
#68
1#
1%
b00000000000000000000000011000100 '
b00000000000000000000000011001100 (
#69
0#
#70
1#
0%
b00000000000000000000000011001100 '
b00000000000000000000000011010000 (
#71
0#
#72
1#
1%
b00000000000000000000000011010000 '
b00000000000000000000000011011000 (
#73
0#
#74
1#
0%
b00000000000000000000000011011000 '
b00000000000000000000000011011100 (
#75
0#
#76
1#
1%
b00000000000000000000000011011100 '
b00000000000000000000000011100100 (
#77
0#
#78
1#
0%
b00000000000000000000000011100100 '
b00000000000000000000000011101000 (
#79
0#
#80
1#
1%
b00000000000000000000000011101000 '
b00000000000000000000000011110000 (
#81
0#
#82
1#
0%
b00000000000000000000000011110000 '
b00000000000000000000000011110100 (
#83
0#
#84
1#
1%
b00000000000000000000000011110100 '
b00000000000000000000000011111100 (
#85
0#
#86
1#
0%
b00000000000000000000000011111100 '
b00000000000000000000000100000000 (
#87
0#
#88
1#
1%
b00000000000000000000000100000000 '
b00000000000000000000000100001000 (
#89
0#
#90
1#
0%
b00000000000000000000000100001000 '
b00000000000000000000000100001100 (
#91
0#
#92
1#
1%
b00000000000000000000000100001100 '
b00000000000000000000000100010100 (
#93
0#
#94
1#
0%
b00000000000000000000000100010100 '
b00000000000000000000000100011000 (
#95
0#
#96
1#
1%
b00000000000000000000000100011000 '
b00000000000000000000000100100000 (
#97
0#
#98
1#
0%
b00000000000000000000000100100000 '
b00000000000000000000000100100100 (
#99
0#
#100
1#
1%
b00000000000000000000000100100100 '
b00000000000000000000000100101100 (
#101
0#
#102
1#
0%
b00000000000000000000000100101100 '
b00000000000000000000000100110000 (
#103
0#
#104
1#
1%
b00000000000000000000000100110000 '
b00000000000000000000000100111000 (
#105
0#
#106
1#
0%
b00000000000000000000000100111000 '
b00000000000000000000000100111100 (
#107
0#
#108
1#
1%
b00000000000000000000000100111100 '
b00000000000000000000000101000100 (
#109
0#
#110
1#
0%
b00000000000000000000000101000100 '
b00000000000000000000000101001000 (
#111
0#
#112
1#
1%
b00000000000000000000000101001000 '
b00000000000000000000000101010000 (
#113
0#
#114
1#
0%
b00000000000000000000000101010000 '
b00000000000000000000000101010100 (
#115
0#
#116
1#
1%
b00000000000000000000000101010100 '
b00000000000000000000000101011100 (
#117
0#
#118
1#
0%
b00000000000000000000000101011100 '
b00000000000000000000000101100000 (
#119
0#
#120
1#
1%
b00000000000000000000000101100000 '
b00000000000000000000000101101000 (
#121
0#
#122
1#
0%
b00000000000000000000000101101000 '
b00000000000000000000000101101100 (
#123
0#
#124
1#
1%
b00000000000000000000000101101100 '
b00000000000000000000000101110100 (
#125
0#
#126
1#
0%
b00000000000000000000000101110100 '
b00000000000000000000000101111000 (
#127
0#
#128
1#
1%
b00000000000000000000000101111000 '
b00000000000000000000000110000000 (
#129
0#
#130
1#
0%
b00000000000000000000000110000000 '
b00000000000000000000000110000100 (
#131
0#
#132
1#
1%
b00000000000000000000000110000100 '
b00000000000000000000000110001100 (
#133
0#
#134
1#
0%
b00000000000000000000000110001100 '
b00000000000000000000000110010000 (
#135
0#
#136
1#
1%
b00000000000000000000000110010000 '
b00000000000000000000000110011000 (
#137
0#
#138
1#
0%
b00000000000000000000000110011000 '
b00000000000000000000000110011100 (
#139
0#
#140
1#
1%
b00000000000000000000000110011100 '
b00000000000000000000000110100100 (
#141
0#
#142
1#
0%
b00000000000000000000000110100100 '
b00000000000000000000000110101000 (
#143
0#
#144
1#
1%
b00000000000000000000000110101000 '
b00000000000000000000000110110000 (
#145
0#
#146
1#
0%
b00000000000000000000000110110000 '
b00000000000000000000000110110100 (
#147
0#
#148
1#
1%
b00000000000000000000000110110100 '
b00000000000000000000000110111100 (
#149
0#
#150
1#
0%
b00000000000000000000000110111100 '
b00000000000000000000000111000000 (
#151
0#
#152
1#
1%
b00000000000000000000000111000000 '
b00000000000000000000000111001000 (
#153
0#
#154
1#
0%
b00000000000000000000000111001000 '
b00000000000000000000000111001100 (
#155
0#
#156
1#
1%
b00000000000000000000000111001100 '
b00000000000000000000000111010100 (
#157
0#
#158
1#
0%
b00000000000000000000000111010100 '
b00000000000000000000000111011000 (
#159
0#
#160
1#
1%
b00000000000000000000000111011000 '
b00000000000000000000000111100000 (
#161
0#
#162
1#
0%
b00000000000000000000000111100000 '
b00000000000000000000000111100100 (
#163
0#
#164
1#
1%
b00000000000000000000000111100100 '
b00000000000000000000000111101100 (
#165
0#
#166
1#
0%
b00000000000000000000000111101100 '
b00000000000000000000000111110000 (
#167
0#
#168
1#
1%
b00000000000000000000000111110000 '
b00000000000000000000000111111000 (
#169
0#
#170
1#
0%
b00000000000000000000000111111000 '
b00000000000000000000000111111100 (
#171
0#
#172
1#
1%
b00000000000000000000000111111100 '
b00000000000000000000001000000100 (
#173
0#
#174
1#
0%
b00000000000000000000001000000100 '
b00000000000000000000001000001000 (
#175
0#
#176
1#
1%
b00000000000000000000001000001000 '
b00000000000000000000001000010000 (
#177
0#
#178
1#
0%
b00000000000000000000001000010000 '
b00000000000000000000001000010100 (
#179
0#
#180
1#
1%
b00000000000000000000001000010100 '
b00000000000000000000001000011100 (
#181
0#
#182
1#
0%
b00000000000000000000001000011100 '
b00000000000000000000001000100000 (
#183
0#
#184
1#
1%
b00000000000000000000001000100000 '
b00000000000000000000001000101000 (
#185
0#
#186
1#
0%
b00000000000000000000001000101000 '
b00000000000000000000001000101100 (
#187
0#
#188
1#
1%
b00000000000000000000001000101100 '
b00000000000000000000001000110100 (
#189
0#
#190
1#
0%
b00000000000000000000001000110100 '
b00000000000000000000001000111000 (
#191
0#
#192
1#
1%
b00000000000000000000001000111000 '
b00000000000000000000001001000000 (
#193
0#
#194
1#
0%
b00000000000000000000001001000000 '
b00000000000000000000001001000100 (
#195
0#
#196
1#
1%
b00000000000000000000001001000100 '
b00000000000000000000001001001100 (
#197
0#
#198
1#
0%
b00000000000000000000001001001100 '
b00000000000000000000001001010000 (
#199
0#
#200
1#
1%
b00000000000000000000001001010000 '
b00000000000000000000001001011000 (
#201
0#
#202
1#
0%
b00000000000000000000001001011000 '
b00000000000000000000001001011100 (
#203
0#
#204
1#
1%
b00000000000000000000001001011100 '
b00000000000000000000001001100100 (
#205
0#
#206
1#
0%
b00000000000000000000001001100100 '
b00000000000000000000001001101000 (
#207
0#
#208
1#
1%
b00000000000000000000001001101000 '
b00000000000000000000001001110000 (
#209
0#
#210
1#
0%
b00000000000000000000001001110000 '
b00000000000000000000001001110100 (
#211
0#
#212
1#
1%
b00000000000000000000001001110100 '
b00000000000000000000001001111100 (
#213
0#
#214
1#
0%
b00000000000000000000001001111100 '
b00000000000000000000001010000000 (
#215
0#
#216
1#
1%
b00000000000000000000001010000000 '
b00000000000000000000001010001000 (
#217
0#
#218
1#
0%
b00000000000000000000001010001000 '
b00000000000000000000001010001100 (
#219
0#
#220
1#
1%
b00000000000000000000001010001100 '
b00000000000000000000001010010100 (
#221
0#
#222
1#
0%
b00000000000000000000001010010100 '
b00000000000000000000001010011000 (
#223
0#
#224
1#
1%
b00000000000000000000001010011000 '
b00000000000000000000001010100000 (
#225
0#
#226
1#
0%
b00000000000000000000001010100000 '
b00000000000000000000001010100100 (
#227
0#
#228
1#
1%
b00000000000000000000001010100100 '
b00000000000000000000001010101100 (
#229
0#
#230
1#
0%
b00000000000000000000001010101100 '
b00000000000000000000001010110000 (
#231
0#
#232
1#
1%
b00000000000000000000001010110000 '
b00000000000000000000001010111000 (
#233
0#
#234
1#
0%
b00000000000000000000001010111000 '
b00000000000000000000001010111100 (
#235
0#
#236
1#
1%
b00000000000000000000001010111100 '
b00000000000000000000001011000100 (
#237
0#
#238
1#
0%
b00000000000000000000001011000100 '
b00000000000000000000001011001000 (
#239
0#
#240
1#
1%
b00000000000000000000001011001000 '
b00000000000000000000001011010000 (
#241
0#
#242
1#
0%
b00000000000000000000001011010000 '
b00000000000000000000001011010100 (
#243
0#
#244
1#
1%
b00000000000000000000001011010100 '
b00000000000000000000001011011100 (
#245
0#
#246
1#
0%
b00000000000000000000001011011100 '
b00000000000000000000001011100000 (
#247
0#
#248
1#
1%
b00000000000000000000001011100000 '
b00000000000000000000001011101000 (
#249
0#
#250
1#
0%
b00000000000000000000001011101000 '
b00000000000000000000001011101100 (
#251
0#
#252
1#
1%
b00000000000000000000001011101100 '
b00000000000000000000001011110100 (
#253
0#
#254
1#
0%
b00000000000000000000001011110100 '
b00000000000000000000001011111000 (
#255
0#
#256
1#
1%
b00000000000000000000001011111000 '
b00000000000000000000001100000000 (
#257
0#
#258
1#
0%
b00000000000000000000001100000000 '
b00000000000000000000001100000100 (
#259
0#
#260
1#
1%
b00000000000000000000001100000100 '
b00000000000000000000001100001100 (
#261
0#
#262
1#
0%
b00000000000000000000001100001100 '
b00000000000000000000001100010000 (
#263
0#
#264
1#
1%
b00000000000000000000001100010000 '
b00000000000000000000001100011000 (
#265
0#
#266
1#
0%
b00000000000000000000001100011000 '
b00000000000000000000001100011100 (
#267
0#
#268
1#
1%
b00000000000000000000001100011100 '
b00000000000000000000001100100100 (
#269
0#
#270
1#
0%
b00000000000000000000001100100100 '
b00000000000000000000001100101000 (
#271
0#
#272
1#
1%
b00000000000000000000001100101000 '
b00000000000000000000001100110000 (
#273
0#
#274
1#
0%
b00000000000000000000001100110000 '
b00000000000000000000001100110100 (
#275
0#
#276
1#
1%
b00000000000000000000001100110100 '
b00000000000000000000001100111100 (
#277
0#
#278
1#
0%
b00000000000000000000001100111100 '
b00000000000000000000001101000000 (
#279
0#
#280
1#
1%
b00000000000000000000001101000000 '
b00000000000000000000001101001000 (
#281
0#
#282
1#
0%
b00000000000000000000001101001000 '
b00000000000000000000001101001100 (
#283
0#
#284
1#
1%
b00000000000000000000001101001100 '
b00000000000000000000001101010100 (
#285
0#
#286
1#
0%
b00000000000000000000001101010100 '
b00000000000000000000001101011000 (
#287
0#
#288
1#
1%
b00000000000000000000001101011000 '
b00000000000000000000001101100000 (
#289
0#
#290
1#
0%
b00000000000000000000001101100000 '
b00000000000000000000001101100100 (
#291
0#
#292
1#
1%
b00000000000000000000001101100100 '
b00000000000000000000001101101100 (
#293
0#
#294
1#
0%
b00000000000000000000001101101100 '
b00000000000000000000001101110000 (
#295
0#
#296
1#
1%
b00000000000000000000001101110000 '
b00000000000000000000001101111000 (
#297
0#
#298
1#
0%
b00000000000000000000001101111000 '
b00000000000000000000001101111100 (
#299
0#
#300
1#
1%
b00000000000000000000001101111100 '
b00000000000000000000001110000100 (
#301
0#
#302
1#
0%
b00000000000000000000001110000100 '
b00000000000000000000001110001000 (
#303
0#
#304
1#
1%
b00000000000000000000001110001000 '
b00000000000000000000001110010000 (
#305
0#
#306
1#
0%
b00000000000000000000001110010000 '
b00000000000000000000001110010100 (
#307
0#
#308
1#
1%
b00000000000000000000001110010100 '
b00000000000000000000001110011100 (
#309
0#
#310
1#
0%
b00000000000000000000001110011100 '
b00000000000000000000001110100000 (
#311
0#
#312
1#
1%
b00000000000000000000001110100000 '
b00000000000000000000001110101000 (
#313
0#
#314
1#
0%
b00000000000000000000001110101000 '
b00000000000000000000001110101100 (
#315
0#
#316
1#
1%
b00000000000000000000001110101100 '
b00000000000000000000001110110100 (
#317
0#
#318
1#
0%
b00000000000000000000001110110100 '
b00000000000000000000001110111000 (
#319
0#
#320
1#
1%
b00000000000000000000001110111000 '
b00000000000000000000001111000000 (
#321
0#
#322
1#
0%
b00000000000000000000001111000000 '
b00000000000000000000001111000100 (
#323
0#
#324
1#
1%
b00000000000000000000001111000100 '
b00000000000000000000001111001100 (
#325
0#
#326
1#
0%
b00000000000000000000001111001100 '
b00000000000000000000001111010000 (
#327
0#
#328
1#
1%
b00000000000000000000001111010000 '
b00000000000000000000001111011000 (
#329
0#
#330
1#
0%
b00000000000000000000001111011000 '
b00000000000000000000001111011100 (
#331
0#
#332
1#
1%
b00000000000000000000001111011100 '
b00000000000000000000001111100100 (
#333
0#
#334
1#
0%
b00000000000000000000001111100100 '
b00000000000000000000001111101000 (
#335
0#
#336
1#
1%
b00000000000000000000001111101000 '
b00000000000000000000001111110000 (
#337
0#
#338
1#
0%
b00000000000000000000001111110000 '
b00000000000000000000001111110100 (
#339
0#
#340
1#
1%
b00000000000000000000001111110100 '
b00000000000000000000001111111100 (
#341
0#
#342
1#
0%
b00000000000000000000001111111100 '
b00000000000000000000010000000000 (
#343
0#
#344
1#
1%
b00000000000000000000010000000000 '
b00000000000000000000010000001000 (
#345
0#
#346
1#
0%
b00000000000000000000010000001000 '
b00000000000000000000010000001100 (
#347
0#
#348
1#
1%
b00000000000000000000010000001100 '
b00000000000000000000010000010100 (
#349
0#
#350
1#
0%
b00000000000000000000010000010100 '
b00000000000000000000010000011000 (
#351
0#
#352
1#
1%
b00000000000000000000010000011000 '
b00000000000000000000010000100000 (
#353
0#
#354
1#
0%
b00000000000000000000010000100000 '
b00000000000000000000010000100100 (
#355
0#
#356
1#
1%
b00000000000000000000010000100100 '
b00000000000000000000010000101100 (
#357
0#
#358
1#
0%
b00000000000000000000010000101100 '
b00000000000000000000010000110000 (
#359
0#
#360
1#
1%
b00000000000000000000010000110000 '
b00000000000000000000010000111000 (
#361
0#
#362
1#
0%
b00000000000000000000010000111000 '
b00000000000000000000010000111100 (
#363
0#
#364
1#
1%
b00000000000000000000010000111100 '
b00000000000000000000010001000100 (
#365
0#
#366
1#
0%
b00000000000000000000010001000100 '
b00000000000000000000010001001000 (
#367
0#
#368
1#
1%
b00000000000000000000010001001000 '
b00000000000000000000010001010000 (
#369
0#
#370
1#
0%
b00000000000000000000010001010000 '
b00000000000000000000010001010100 (
#371
0#
#372
1#
1%
b00000000000000000000010001010100 '
b00000000000000000000010001011100 (
#373
0#
#374
1#
0%
b00000000000000000000010001011100 '
b00000000000000000000010001100000 (
#375
0#
#376
1#
1%
b00000000000000000000010001100000 '
b00000000000000000000010001101000 (
#377
0#
#378
1#
0%
b00000000000000000000010001101000 '
b00000000000000000000010001101100 (
#379
0#
#380
1#
1%
b00000000000000000000010001101100 '
b00000000000000000000010001110100 (
#381
0#
#382
1#
0%
b00000000000000000000010001110100 '
b00000000000000000000010001111000 (
#383
0#
#384
1#
1%
b00000000000000000000010001111000 '
b00000000000000000000010010000000 (
#385
0#
#386
1#
0%
b00000000000000000000010010000000 '
b00000000000000000000010010000100 (
#387
0#
#388
1#
1%
b00000000000000000000010010000100 '
b00000000000000000000010010001100 (
#389
0#
#390
1#
0%
b00000000000000000000010010001100 '
b00000000000000000000010010010000 (
#391
0#
#392
1#
1%
b00000000000000000000010010010000 '
b00000000000000000000010010011000 (
#393
0#
#394
1#
0%
b00000000000000000000010010011000 '
b00000000000000000000010010011100 (
#395
0#
#396
1#
1%
b00000000000000000000010010011100 '
b00000000000000000000010010100100 (
#397
0#
#398
1#
0%
b00000000000000000000010010100100 '
b00000000000000000000010010101000 (
#399
0#
#400
1#
1%
b00000000000000000000010010101000 '
b00000000000000000000010010110000 (
#401
0#
#402
1#
0%
b00000000000000000000010010110000 '
b00000000000000000000010010110100 (
#403
0#
#404
1#
1%
b00000000000000000000010010110100 '
b00000000000000000000010010111100 (
#405
0#
#406
1#
0%
b00000000000000000000010010111100 '
b00000000000000000000010011000000 (
#407
0#
#408
1#
1%
b00000000000000000000010011000000 '
b00000000000000000000010011001000 (
#409
0#
#410
1#
0%
b00000000000000000000010011001000 '
b00000000000000000000010011001100 (
#411
0#
#412
1#
1%
b00000000000000000000010011001100 '
b00000000000000000000010011010100 (
#413
0#
#414
1#
0%
b00000000000000000000010011010100 '
b00000000000000000000010011011000 (
#415
0#
#416
1#
1%
b00000000000000000000010011011000 '
b00000000000000000000010011100000 (
#417
0#
#418
1#
0%
b00000000000000000000010011100000 '
b00000000000000000000010011100100 (
#419
0#
#420
1#
1%
b00000000000000000000010011100100 '
b00000000000000000000010011101100 (
#421
0#
#422
1#
0%
b00000000000000000000010011101100 '
b00000000000000000000010011110000 (
#423
0#
#424
1#
1%
b00000000000000000000010011110000 '
b00000000000000000000010011111000 (
#425
0#
#426
1#
0%
b00000000000000000000010011111000 '
b00000000000000000000010011111100 (
#427
0#
#428
1#
1%
b00000000000000000000010011111100 '
b00000000000000000000010100000100 (
#429
0#
#430
1#
0%
b00000000000000000000010100000100 '
b00000000000000000000010100001000 (
#431
0#
#432
1#
1%
b00000000000000000000010100001000 '
b00000000000000000000010100010000 (
#433
0#
#434
1#
0%
b00000000000000000000010100010000 '
b00000000000000000000010100010100 (
#435
0#
#436
1#
1%
b00000000000000000000010100010100 '
b00000000000000000000010100011100 (
#437
0#
#438
1#
0%
b00000000000000000000010100011100 '
b00000000000000000000010100100000 (
#439
0#
#440
1#
1%
b00000000000000000000010100100000 '
b00000000000000000000010100101000 (
#441
0#
#442
1#
0%
b00000000000000000000010100101000 '
b00000000000000000000010100101100 (
#443
0#
#444
1#
1%
b00000000000000000000010100101100 '
b00000000000000000000010100110100 (
#445
0#
#446
1#
0%
b00000000000000000000010100110100 '
b00000000000000000000010100111000 (
#447
0#
#448
1#
1%
b00000000000000000000010100111000 '
b00000000000000000000010101000000 (
#449
0#
#450
1#
0%
b00000000000000000000010101000000 '
b00000000000000000000010101000100 (
#451
0#
#452
1#
1%
b00000000000000000000010101000100 '
b00000000000000000000010101001100 (
#453
0#
#454
1#
0%
b00000000000000000000010101001100 '
b00000000000000000000010101010000 (
#455
0#
#456
1#
1%
b00000000000000000000010101010000 '
b00000000000000000000010101011000 (
#457
0#
#458
1#
0%
b00000000000000000000010101011000 '
b00000000000000000000010101011100 (
#459
0#
#460
1#
1%
b00000000000000000000010101011100 '
b00000000000000000000010101100100 (
#461
0#
#462
1#
0%
b00000000000000000000010101100100 '
b00000000000000000000010101101000 (
#463
0#
#464
1#
1%
b00000000000000000000010101101000 '
b00000000000000000000010101110000 (
#465
0#
#466
1#
0%
b00000000000000000000010101110000 '
b00000000000000000000010101110100 (
#467
0#
#468
1#
1%
b00000000000000000000010101110100 '
b00000000000000000000010101111100 (
#469
0#
#470
1#
0%
b00000000000000000000010101111100 '
b00000000000000000000010110000000 (
#471
0#
#472
1#
1%
b00000000000000000000010110000000 '
b00000000000000000000010110001000 (
#473
0#
#474
1#
0%
b00000000000000000000010110001000 '
b00000000000000000000010110001100 (
#475
0#
#476
1#
1%
b00000000000000000000010110001100 '
b00000000000000000000010110010100 (
#477
0#
#478
1#
0%
b00000000000000000000010110010100 '
b00000000000000000000010110011000 (
#479
0#
#480
1#
1%
b00000000000000000000010110011000 '
b00000000000000000000010110100000 (
#481
0#
#482
1#
0%
b00000000000000000000010110100000 '
b00000000000000000000010110100100 (
#483
0#
#484
1#
1%
b00000000000000000000010110100100 '
b00000000000000000000010110101100 (
#485
0#
#486
1#
0%
b00000000000000000000010110101100 '
b00000000000000000000010110110000 (
#487
0#
#488
1#
1%
b00000000000000000000010110110000 '
b00000000000000000000010110111000 (
#489
0#
#490
1#
0%
b00000000000000000000010110111000 '
b00000000000000000000010110111100 (
#491
0#
#492
1#
1%
b00000000000000000000010110111100 '
b00000000000000000000010111000100 (
#493
0#
#494
1#
0%
b00000000000000000000010111000100 '
b00000000000000000000010111001000 (
#495
0#
#496
1#
1%
b00000000000000000000010111001000 '
b00000000000000000000010111010000 (
#497
0#
#498
1#
0%
b00000000000000000000010111010000 '
b00000000000000000000010111010100 (
#499
0#
#500
1#
1%
b00000000000000000000010111010100 '
b00000000000000000000010111011100 (
#501
0#
#502
1#
0%
b00000000000000000000010111011100 '
b00000000000000000000010111100000 (
#503
0#
#504
1#
1%
b00000000000000000000010111100000 '
b00000000000000000000010111101000 (
#505
0#
#506
1#
0%
b00000000000000000000010111101000 '
b00000000000000000000010111101100 (
#507
0#
#508
1#
1%
b00000000000000000000010111101100 '
b00000000000000000000010111110100 (
#509
0#
#510
1#
0%
b00000000000000000000010111110100 '
b00000000000000000000010111111000 (
#511
0#
#512
1#
1%
b00000000000000000000010111111000 '
b00000000000000000000011000000000 (
#513
0#
#514
1#
0%
b00000000000000000000011000000000 '
b00000000000000000000011000000100 (
#515
0#
#516
1#
1%
b00000000000000000000011000000100 '
b00000000000000000000011000001100 (
#517
0#
#518
1#
0%
b00000000000000000000011000001100 '
b00000000000000000000011000010000 (
#519
0#
#520
1#
1%
b00000000000000000000011000010000 '
b00000000000000000000011000011000 (
#521
0#
#522
1#
0%
b00000000000000000000011000011000 '
b00000000000000000000011000011100 (
#523
0#
#524
1#
1%
b00000000000000000000011000011100 '
b00000000000000000000011000100100 (
#525
0#
#526
1#
0%
b00000000000000000000011000100100 '
b00000000000000000000011000101000 (
#527
0#
#528
1#
1%
b00000000000000000000011000101000 '
b00000000000000000000011000110000 (
#529
0#
#530
1#
0%
b00000000000000000000011000110000 '
b00000000000000000000011000110100 (
#531
0#
#532
1#
1%
b00000000000000000000011000110100 '
b00000000000000000000011000111100 (
#533
0#
#534
1#
0%
b00000000000000000000011000111100 '
b00000000000000000000011001000000 (
#535
0#
#536
1#
1%
b00000000000000000000011001000000 '
b00000000000000000000011001001000 (
#537
0#
#538
1#
0%
b00000000000000000000011001001000 '
b00000000000000000000011001001100 (
#539
0#
#540
1#
1%
b00000000000000000000011001001100 '
b00000000000000000000011001010100 (
#541
0#
#542
1#
0%
b00000000000000000000011001010100 '
b00000000000000000000011001011000 (
#543
0#
#544
1#
1%
b00000000000000000000011001011000 '
b00000000000000000000011001100000 (
#545
0#
#546
1#
0%
b00000000000000000000011001100000 '
b00000000000000000000011001100100 (
#547
0#
#548
1#
1%
b00000000000000000000011001100100 '
b00000000000000000000011001101100 (
#549
0#
#550
1#
0%
b00000000000000000000011001101100 '
b00000000000000000000011001110000 (
#551
0#
#552
1#
1%
b00000000000000000000011001110000 '
b00000000000000000000011001111000 (
#553
0#
#554
1#
0%
b00000000000000000000011001111000 '
b00000000000000000000011001111100 (
#555
0#
#556
1#
1%
b00000000000000000000011001111100 '
b00000000000000000000011010000100 (
#557
0#
#558
1#
0%
b00000000000000000000011010000100 '
b00000000000000000000011010001000 (
#559
0#
#560
1#
1%
b00000000000000000000011010001000 '
b00000000000000000000011010010000 (
#561
0#
#562
1#
0%
b00000000000000000000011010010000 '
b00000000000000000000011010010100 (
#563
0#
#564
1#
1%
b00000000000000000000011010010100 '
b00000000000000000000011010011100 (
#565
0#
#566
1#
0%
b00000000000000000000011010011100 '
b00000000000000000000011010100000 (
#567
0#
#568
1#
1%
b00000000000000000000011010100000 '
b00000000000000000000011010101000 (
#569
0#
#570
1#
0%
b00000000000000000000011010101000 '
b00000000000000000000011010101100 (
#571
0#
#572
1#
1%
b00000000000000000000011010101100 '
b00000000000000000000011010110100 (
#573
0#
#574
1#
0%
b00000000000000000000011010110100 '
b00000000000000000000011010111000 (
#575
0#
#576
1#
1%
b00000000000000000000011010111000 '
b00000000000000000000011011000000 (
#577
0#
#578
1#
0%
b00000000000000000000011011000000 '
b00000000000000000000011011000100 (
#579
0#
#580
1#
1%
b00000000000000000000011011000100 '
b00000000000000000000011011001100 (
#581
0#
#582
1#
0%
b00000000000000000000011011001100 '
b00000000000000000000011011010000 (
#583
0#
#584
1#
1%
b00000000000000000000011011010000 '
b00000000000000000000011011011000 (
#585
0#
#586
1#
0%
b00000000000000000000011011011000 '
b00000000000000000000011011011100 (
#587
0#
#588
1#
1%
b00000000000000000000011011011100 '
b00000000000000000000011011100100 (
#589
0#
#590
1#
0%
b00000000000000000000011011100100 '
b00000000000000000000011011101000 (
#591
0#
#592
1#
1%
b00000000000000000000011011101000 '
b00000000000000000000011011110000 (
#593
0#
#594
1#
0%
b00000000000000000000011011110000 '
b00000000000000000000011011110100 (
#595
0#
#596
1#
1%
b00000000000000000000011011110100 '
b00000000000000000000011011111100 (
#597
0#
#598
1#
0%
b00000000000000000000011011111100 '
b00000000000000000000011100000000 (
